bnusys/__init__.py
bnusys/basics.py
bnusys/core_cuda.cu
bnusys/gpu_ops.py
bnusys/lib_bnusys.dll
bnusys/math.py
bnusys/sparse.py
bnusys/sparse_ops.py
bnusys-0.1.0.dist-info/licenses/License
bnusys-0.1.0.dist-info/METADATA
bnusys-0.1.0.dist-info/WHEEL
bnusys-0.1.0.dist-info/top_level.txt
bnusys-0.1.0.dist-info/RECORD
