Metadata-Version: 2.4
Name: bnusys
Version: 0.1.0
Summary: A sparse matrix library with CUDA acceleration.
Author-email: Marvin <202522081036@mail.bnu.edu.cn>
License: MIT
Project-URL: Homepage, https://github.com/bnusys
Project-URL: Source, https://github.com/Seto1919810/bnusys
Requires-Python: >=3.8
License-File: License
Requires-Dist: numpy
Provides-Extra: test
Requires-Dist: pytest; extra == "test"
Dynamic: license-file
